LICENSE
README.md
setup.py
brainspy_smg.egg-info/PKG-INFO
brainspy_smg.egg-info/SOURCES.txt
brainspy_smg.egg-info/dependency_links.txt
brainspy_smg.egg-info/not-zip-safe
brainspy_smg.egg-info/requires.txt
brainspy_smg.egg-info/top_level.txt
bspysmg/__init__.py
bspysmg/data/__init__.py
bspysmg/data/dataset.py
bspysmg/data/postprocess.py
bspysmg/data/sampling.py
bspysmg/model/__init__.py
bspysmg/model/training.py
bspysmg/utils/__init__.py
bspysmg/utils/consistency.py
bspysmg/utils/inputs.py
bspysmg/utils/plots.py
bspysmg/utils/iv/__init__.py
bspysmg/utils/iv/multiple.py
bspysmg/utils/iv/simple.py
tests/__init__.py
tests/main.py
tests/unit/__init__.py
tests/unit/test_consistency.py
tests/unit/test_dataset.py
tests/unit/test_inputs.py
tests/unit/test_multiple.py
tests/unit/test_plots.py
tests/unit/test_postprocess.py
tests/unit/test_sampling.py
tests/unit/test_simple.py
tests/unit/test_training.py