Metadata-Version: 2.1
Name: brainspy-smg
Version: 1.0.6
Summary: A python package to support research on different nano-scale materials for creating hardware accelerators in the context of deep neural networks.
Home-page: https://github.com/BraiNEdarwin/brainspy-smg
Author: Unai Alegre-Ibarra et al.
Author-email: u.alegre@utwente.nl
License: GPL-3.0
Keywords: pytorch,nano,material,hardware acceleration,deep neural networks,surrogate model,twin device
Platform: UNKNOWN
Classifier: Development Status :: 5 - Production/Stable
Classifier: Topic :: Scientific/Engineering :: Artificial Intelligence
Classifier: Intended Audience :: Science/Research
Classifier: Programming Language :: Python :: 3.9
Classifier: License :: OSI Approved :: GNU General Public License v3 (GPLv3)
License-File: LICENSE
